setup.py
autocli/__init__.py
autocli/_obj.py
autocli.egg-info/PKG-INFO
autocli.egg-info/SOURCES.txt
autocli.egg-info/dependency_links.txt
autocli.egg-info/requires.txt
autocli.egg-info/top_level.txt