Metadata-Version: 1.1
Name: autocli
Version: 0.6
Summary: Builds command line interfaces to parse objects or call functions
Home-page: https://github.com/nikhilk/autocli
Author: Nikhil Kothari
Author-email: UNKNOWN
License: BSD
Keywords: argparse automatic cli parser
Platform: UNKNOWN
Classifier: Development Status :: 3 - Alpha
Classifier: Environment :: Console
Classifier: Topic :: Utilities
Classifier: License :: OSI Approved :: BSD License
